setup.cfg
setup.py
SecretManagerEnvInjector/__init__.py
SecretManagerEnvInjector/secret_extractor.py
SecretManagerEnvInjector/exceptions/__init__.py
SecretManagerEnvInjector/exceptions/invalid_input.py
secret_manager_env_injector.egg-info/PKG-INFO
secret_manager_env_injector.egg-info/SOURCES.txt
secret_manager_env_injector.egg-info/dependency_links.txt
secret_manager_env_injector.egg-info/requires.txt
secret_manager_env_injector.egg-info/top_level.txt
test/__init__.py
test/test_inject.py