Metadata-Version: 2.1
Name: secret-manager-env-injector
Version: 0.0.3
Summary: A plug-n-play package fetch secrets form secret manager and insert them in the env
Home-page: https://github.com/Bharat23/secret-manager-env-injector
Author: Bharat Sinha
Author-email: bharat.sinha.2307@gmail.com
License: MIT
Keywords: AWS,secret manager,env,cloud,json
Platform: UNKNOWN
Classifier: Programming Language :: Python :: 3
Classifier: License :: OSI Approved :: MIT License
Classifier: Operating System :: OS Independent
Classifier: Intended Audience :: Developers
Requires-Python: >=3.6
